README.rst
setup.py
src/sc_tool.egg-info/PKG-INFO
src/sc_tool.egg-info/SOURCES.txt
src/sc_tool.egg-info/dependency_links.txt
src/sc_tool.egg-info/entry_points.txt
src/sc_tool.egg-info/top_level.txt
src/shimmercat/__init__.py
src/shimmercat/tools/__init__.py
src/shimmercat/tools/api.py
src/shimmercat/tools/config_webdrivers.py
src/shimmercat/tools/sc_chrome.py
src/shimmercat/tools/sc_instca.py
src/shimmercat/tools/sc_learn.py
src/shimmercat/tools/sc_tool.py