Metadata-Version: 1.1
Name: sc-tool
Version: 1.1.0
Summary: ShimmerCat's administrative tools
Home-page: https://www.shimmercat.com/
Author: Alcides Viamontes Esquivel
Author-email: alcidesv@zunzun.se
License: BSD3
Keywords: shimmercat
Platform: UNKNOWN
Classifier: Development Status :: 4 - Beta
Classifier: Intended Audience :: Developers
Classifier: Topic :: Software Development :: Build Tools
Classifier: Programming Language :: Python :: 2.7
